deep_lc/__init__.py
deep_lc/anchors.py
deep_lc/classifier.py
deep_lc/config.py
deep_lc/conformal.py
deep_lc/conformal_utils.py
deep_lc/dataset.py
deep_lc/finetune.py
deep_lc/models.py
deep_lc/resnet.py
deep_lc/utils.py
deep_lightcurve-0.1.1.dist-info/licenses/LICENSE
deep_lightcurve-0.1.1.dist-info/METADATA
deep_lightcurve-0.1.1.dist-info/WHEEL
deep_lightcurve-0.1.1.dist-info/top_level.txt
deep_lightcurve-0.1.1.dist-info/RECORD
