Metadata-Version: 2.4
Name: Deep-Lightcurve
Version: 0.1.1
Summary: A general Light curve classification framework based on deep learning
Author-email: Kaiming Cui <cuikaiming6@gmail.com>
License: MIT License
Project-URL: Homepage, https://github.com/ckm3/Deep-LC
Classifier: Development Status :: 5 - Production/Stable
Classifier: Intended Audience :: Science/Research
Classifier: Operating System :: OS Independent
Classifier: Programming Language :: Python :: 3
Classifier: Topic :: Scientific/Engineering :: Astronomy
Classifier: Topic :: Scientific/Engineering :: Physics
Requires-Python: >=3.8
License-File: LICENSE
Requires-Dist: torch
Requires-Dist: torchvision
Requires-Dist: gatspy
Requires-Dist: lightkurve>=2.0
Requires-Dist: lightkurve-ext>=0.1.1
Provides-Extra: dev
Requires-Dist: black; extra == "dev"
Requires-Dist: bumpver; extra == "dev"
Requires-Dist: isort; extra == "dev"
Requires-Dist: pip-tools; extra == "dev"
Requires-Dist: pytest; extra == "dev"
Dynamic: license-file
